{
    "$schema": "http://schema.management.azure.com/schemas/2015-01-01/deploymentTemplate.json#",
    "contentVersion": "1.0.0.0",
    "parameters": {
        "networkSecurityGroupName": {
            "type": "string"
        },
        "location": {
            "type": "string"
        }
    },
    "variables": {},
    "resources": [
        {
            "name": "[parameters('networkSecurityGroupName')]",
            "type": "Microsoft.Network/networkSecurityGroups",
            "apiVersion": "2018-08-01",
            "location": "[parameters('location')]",
            "properties": {
                "securityRules": [
                    {
                        "name": "HTTPS",
                        "properties": {
                            "priority": 300,
                            "protocol": "Tcp",
                            "access": "Allow",
                            "direction": "Inbound",
                            "sourceAddressPrefix": "*",
                            "sourcePortRange": "*",
                            "destinationAddressPrefix": "*",
                            "destinationPortRange": "443"
                        }
                    }
                ]
            },
            "tags": {}
        }
    ]
}